setup.cfg
setup.py
bin/newscrape
newscraper/__init__.py
newscraper/commons.py
newscraper/newscrape.py
newscraper/sites.py
newscraper.egg-info/PKG-INFO
newscraper.egg-info/SOURCES.txt
newscraper.egg-info/dependency_links.txt
newscraper.egg-info/requires.txt
newscraper.egg-info/top_level.txt