Metadata-Version: 1.1
Name: newscraper
Version: 0.2
Summary: Scrapes Indian news sites for news related to keywords
Home-page: https://github.com/thekindlyone/newscraper
Author: thekindlyone
Author-email: dodo.dodder@gmail.com
License: GNU GPL v2
Download-URL: https://github.com/thekindlyone/newscraper/tarball/0.2
Keywords: indian,news,scraping
Platform: UNKNOWN
